taskfarm_worker/__init__.py
taskfarm_worker/__version__.py
taskfarm_worker/manage.py
taskfarm_worker/taskfarm.py
taskfarm_worker-0.4.0.dist-info/LICENSE
taskfarm_worker-0.4.0.dist-info/METADATA
taskfarm_worker-0.4.0.dist-info/WHEEL
taskfarm_worker-0.4.0.dist-info/entry_points.txt
taskfarm_worker-0.4.0.dist-info/top_level.txt
taskfarm_worker-0.4.0.dist-info/zip-safe
taskfarm_worker-0.4.0.dist-info/RECORD
